wa_automate_socket_client/__init__.py
wa_automate_socket_client-1.2.0.dist-info/LICENSE.txt
wa_automate_socket_client-1.2.0.dist-info/METADATA
wa_automate_socket_client-1.2.0.dist-info/WHEEL
wa_automate_socket_client-1.2.0.dist-info/top_level.txt
wa_automate_socket_client-1.2.0.dist-info/RECORD
